{{
    "name": "pywal",
    "flavour": "default",
    "mode": "dark",
    "variant": "vibrant",
    "colours": {{
        "primary_paletteKeyColor": "{color4.strip}",
        "secondary_paletteKeyColor": "{color5.strip}",
        "tertiary_paletteKeyColor": "{color6.strip}",
        "neutral_paletteKeyColor": "{color8.strip}",
        "neutral_variant_paletteKeyColor": "{color8.strip}",
        "background": "{background.strip}",
        "onBackground": "{foreground.strip}",
        "surface": "{background.strip}",
        "surfaceDim": "{background.strip}",
        "surfaceBright": "{color8.strip}",
        "surfaceContainerLowest": "{color0.strip}",
        "surfaceContainerLow": "{color0.strip}",
        "surfaceContainer": "{color0.strip}",
        "surfaceContainerHigh": "{color8.strip}",
        "surfaceContainerHighest": "{color8.strip}",
        "onSurface": "{foreground.strip}",
        "surfaceVariant": "{color8.strip}",
        "onSurfaceVariant": "{color7.strip}",
        "inverseSurface": "{foreground.strip}",
        "inverseOnSurface": "{background.strip}",
        "outline": "{color8.strip}",
        "outlineVariant": "{color8.strip}",
        "shadow": "000000",
        "scrim": "000000",
        "surfaceTint": "{color4.strip}",
        "primary": "{color4.strip}",
        "onPrimary": "{background.strip}",
        "primaryContainer": "{color4.strip}",
        "onPrimaryContainer": "{foreground.strip}",
        "inversePrimary": "{color12.strip}",
        "secondary": "{color5.strip}",
        "onSecondary": "{background.strip}",
        "secondaryContainer": "{color5.strip}",
        "onSecondaryContainer": "{foreground.strip}",
        "tertiary": "{color6.strip}",
        "onTertiary": "{background.strip}",
        "tertiaryContainer": "{color6.strip}",
        "onTertiaryContainer": "{foreground.strip}",
        "error": "{color1.strip}",
        "onError": "{background.strip}",
        "errorContainer": "{color1.strip}",
        "onErrorContainer": "{foreground.strip}",
        "primaryFixed": "{color12.strip}",
        "primaryFixedDim": "{color4.strip}",
        "onPrimaryFixed": "{background.strip}",
        "onPrimaryFixedVariant": "{color0.strip}",
        "secondaryFixed": "{color13.strip}",
        "secondaryFixedDim": "{color5.strip}",
        "onSecondaryFixed": "{background.strip}",
        "onSecondaryFixedVariant": "{color0.strip}",
        "tertiaryFixed": "{color14.strip}",
        "tertiaryFixedDim": "{color6.strip}",
        "onTertiaryFixed": "{background.strip}",
        "onTertiaryFixedVariant": "{color0.strip}",
        "term0": "{color0.strip}",
        "term1": "{color1.strip}",
        "term2": "{color2.strip}",
        "term3": "{color3.strip}",
        "term4": "{color4.strip}",
        "term5": "{color5.strip}",
        "term6": "{color6.strip}",
        "term7": "{color7.strip}",
        "term8": "{color8.strip}",
        "term9": "{color9.strip}",
        "term10": "{color10.strip}",
        "term11": "{color11.strip}",
        "term12": "{color12.strip}",
        "term13": "{color13.strip}",
        "term14": "{color14.strip}",
        "term15": "{color15.strip}",
        "rosewater": "{color7.strip}",
        "flamingo": "{color7.strip}",
        "pink": "{color5.strip}",
        "mauve": "{color4.strip}",
        "red": "{color1.strip}",
        "maroon": "{color1.strip}",
        "peach": "{color3.strip}",
        "yellow": "{color3.strip}",
        "green": "{color2.strip}",
        "teal": "{color6.strip}",
        "sky": "{color6.strip}",
        "sapphire": "{color4.strip}",
        "blue": "{color4.strip}",
        "lavender": "{color4.strip}",
        "klink": "{color4.strip}",
        "klinkSelection": "{color12.strip}",
        "kvisited": "{color5.strip}",
        "kvisitedSelection": "{color13.strip}",
        "knegative": "{color1.strip}",
        "knegativeSelection": "{color9.strip}",
        "kneutral": "{color3.strip}",
        "kneutralSelection": "{color11.strip}",
        "kpositive": "{color2.strip}",
        "kpositiveSelection": "{color10.strip}",
        "text": "{foreground.strip}",
        "subtext1": "{color7.strip}",
        "subtext0": "{color8.strip}",
        "overlay2": "{color8.strip}",
        "overlay1": "{color8.strip}",
        "overlay0": "{color8.strip}",
        "surface2": "{color8.strip}",
        "surface1": "{color0.strip}",
        "surface0": "{color0.strip}",
        "base": "{background.strip}",
        "mantle": "{background.strip}",
        "crust": "{color0.strip}",
        "success": "{color2.strip}",
        "onSuccess": "{background.strip}",
        "successContainer": "{color2.strip}",
        "onSuccessContainer": "{foreground.strip}"
    }}
}}
